Metadata-Version: 1.0
Name: gameoflifepython
Version: 1.0.3
Summary: Game of Life implemented with PyGame.
Home-page: UNKNOWN
Author: FKH
Author-email: UNKNOWN
License: GPL-3.0
Platform: UNKNOWN
